payline/__init__.py
payline-1.0.13.dist-info/DESCRIPTION.rst
payline-1.0.13.dist-info/METADATA
payline-1.0.13.dist-info/RECORD
payline-1.0.13.dist-info/WHEEL
payline-1.0.13.dist-info/metadata.json
payline-1.0.13.dist-info/top_level.txt
