Metadata-Version: 2.0
Name: payline
Version: 1.0.13
Summary: Payline API Python client
Home-page: https://paylinedata.com/
Author: Payline Data
Author-email: support@paylinedata.com
License: MIT License
Platform: UNKNOWN
Classifier: Intended Audience :: Developers
Classifier: License :: OSI Approved :: MIT License
Classifier: Programming Language :: Python
Classifier: Topic :: Software Development :: Libraries :: Python Modules
Requires-Dist: finix (==1.0.13)
Provides-Extra: tests
Requires-Dist: coverage (==4.0.3); extra == 'tests'
